i2a_oauth2_api_client/__init__.py
i2a_oauth2_api_client/client.py
i2a_oauth2_api_client/enums.py
i2a_oauth2_api_client/exceptions.py
i2a_oauth2_api_client/types.py
i2a_oauth2_api_client/validators.py
i2a_oauth2_api_client-3.0.4.dist-info/LICENSE.txt
i2a_oauth2_api_client-3.0.4.dist-info/METADATA
i2a_oauth2_api_client-3.0.4.dist-info/WHEEL
i2a_oauth2_api_client-3.0.4.dist-info/top_level.txt
i2a_oauth2_api_client-3.0.4.dist-info/RECORD
