Metadata-Version: 2.1
Name: i2a-oauth2-api-client
Version: 3.0.4
Summary: Sdk for i2a oauth2 api
Download-URL: https://pypi.org/project/i2a_oauth2_api_client/
Author: i2a Solutions Inc.
Author-email: msyta@i2asolutions.com
License: MIT
Keywords: I2A Oauth2 Client,I2A Oauth2 Api,I2A Oauth2,Python 3,I2A Oauth2 Api SDK
License-File: LICENSE.txt
Requires-Dist: requests (>=2.26.0)
